Workbook

Sheet Dashboard
B1: DASHBOARD DE TESIS — RED GPON PARA VIDEOVIGILANCIA URBANA
B2: Planificación de implementación GPON · Bernardo de Irigoyen, Misiones, Argentina
B6: AVANCE GLOBAL | D6: RIESGOS ROJOS | F6: EJEC. INFRAEST. | G6: ESFUERZO ACADÉMICO | I6: ALERTAS ABIERTAS
B7: =TEXT(AVERAGE(Cronograma!F2:F8),"0%") -> 56% | D7: =COUNTIF(Riesgos!G2:G11,"Rojo") -> 2 | F7: "0%" | G7: =TEXT(560/2880,"0.0%") -> 19.4% | I7: =COUNTIF(Alertas!G2:G6,"Abierta")+COUNTIF(Alertas!G2:G6,"En curso") -> 5
B8: promedio de fases | D8: activos | F8: USD 0 ejecutado | G8: 70h / 360h × USD 8 | I8: abiertas + en curso
B11: 📅 CRONOGRAMA — AVANCE POR FASE | G11: 🚦 SEMÁFORO DE RIESGOS
B12: FASE | D12: AVANCE | F12: ESTADO | G12: 🔴 RIESGOS ROJOS
B13: Inicio y alcance | D13: =Cronograma!F2 -> 1 | F13: =Cronograma!H2 -> Finalizado | G13: =COUNTIF(Riesgos!G2:G11,"Rojo") -> 2
B14: Rev. bibliográfica | D14: =Cronograma!F3 -> 1 | F14: =Cronograma!H3 -> Finalizado
B15: Relevamiento/req. | D15: =Cronograma!F4 -> 0.9 | F15: =Cronograma!H4 -> En curso | G15: 🟡 RIESGOS AMARILLOS
B16: Diseño técnico GPON | D16: =Cronograma!F5 -> 0.45 | F16: =Cronograma!H5 -> Atrasado | G16: =COUNTIF(Riesgos!G2:G11,"Amarillo") -> 7
B17: Análisis financiero | D17: =Cronograma!F6 -> 0.35 | F17: =Cronograma!H6 -> Atrasado
B18: Gestión/riesgos/dashboard | D18: =Cronograma!F7 -> 0.15 | F18: =Cronograma!H7 -> Atrasado | G18: 🟢 RIESGOS VERDES
B19: Redacción y defensa | D19: =Cronograma!F8 -> 0.05 | F19: =Cronograma!H8 -> Atrasado | G19: =COUNTIF(Riesgos!G2:G11,"Verde") -> 1
B23: 💰 PRESUPUESTO ESTIMADO vs EJECUTADO REAL | G23: 📈 KPIs — CUMPLIMIENTO NORMALIZADO
B24: CONCEPTO | D24: ESTIMADO | F24: EJECUTADO | G24: KPI | I24: CUMPLIMIENTO
B25: CAPEX infraestructura | D25: =Presupuesto!B2 -> 120730.72 | F25: =Presupuesto!C2 -> 0 | G25: KPI-01 Redacción | I25: =KPIs!I2 -> 0.52941176
B26: OPEX Año 1 | D26: =Presupuesto!B3 -> 31325.58 | F26: =Presupuesto!C3 -> 0 | G26: KPI-02 Cronograma | I26: =KPIs!I3 -> 0.94117647
B27: Esfuerzo académico | D27: =Presupuesto!B4 -> 2880 | F27: =Presupuesto!C4 -> 560 | G27: KPI-04 Valid. técnica | I27: =KPIs!I5 -> 0.6
B28: Nec. presup. 5 años | D28: =Presupuesto!B8 -> 299115.53 | F28: =Presupuesto!C8 -> 0 | G28: KPI-05 An. financiero | I28: =KPIs!I6 -> 0.5
G29: KPI-06 Consignas | I29: =KPIs!I7 -> 0.8
B30: CAPEX estimado | C30: OPEX Año 1 | D30: Benef. Soc. Año 1 | E30: VAN socioeconómico | F30: VAN estatal | G30: KPI-03 Riesgos crít. | I30: =KPIs!I4 -> 1.5
B31: =Presupuesto!B2 -> 120730.72 | C31: =Presupuesto!B3 -> 31325.58 | D31: =Presupuesto!B5 -> 93360 | E31: =Presupuesto!B6 -> 90175.2 | F31: =Presupuesto!B7 -> -239413.53 | G31: KPI-07 Coherencia | I31: =KPIs!I8 -> 0.91836735
B34: ⚠️ ALERTAS Y CUELLOS DE BOTELLA
B35: ALERTA | D35: SEV. | E35: ORIGEN | F35: ACCIÓN REQUERIDA | I35: RESP. | J35: ESTADO
B36: Validar permisos postación EMSA/TVC5 | D36: Alta | E36: R3 | F36: Solicitar respuesta formal y rutas alt. | I36: Municipio | J36: Abierta
B37: Confirmar stock OLT/switches | D37: Alta | E37: R1 | F37: Cotizar con al menos dos vendors | I37: Área técn. | J37: Abierta
B38: Auditar coherencia CAPEX/VAN docs | D38: Media | E38: R10 | F38: Congelar versión y revisar valores | I38: Tesista | J38: Abierta
B39: Cerrar diseño GPON (ruta crítica) | D39: Alta | E39: Ruta crit. | F39: Validar topología y mem. técnica | I39: Tesista | J39: En curso
B40: Actualizar progreso semanal Gantt | D40: Media | E40: Dashboard | F40: Registrar avance por fase | I40: Tesista | J40: En curso
B42: Proyecto: Planificación GPON Videovigilancia Urbana · Bernardo de Irigoyen, Misiones · Actualizar datos en hojas fuente

Sheet Config
A1: Parámetro | B1: Valor | C1: Descripción | D1: Uso
A2: Fecha inicio | B2: 02/03/2026 | C2: Inicio académico estimado | D2: Cronograma
A3: Fecha defensa | B3: 30/11/2026 | C3: Defensa final de tesis | D3: Cronograma
A4: CAPEX | B4: 120730.72 | C4: Inversión inicial infraestructura GPON | D4: Presupuesto
A5: OPEX Año 1 | B5: 31325.58 | C5: Operación y mantenimiento año 1 | D5: Presupuesto
A6: VAN Social | B6: 90175.2 | C6: Escenario con recupero por beneficios | D6: Finanzas
A7: VAN Estatal | B7: -239413.53 | C7: Proyecto estatal asumido a pérdida | D7: Finanzas
A8: Disponibilidad objetivo | B8: 99% | C8: Nivel mínimo esperado | D8: KPI técnico
A9: Latencia máxima | B9: 100 ms | C9: Latencia máxima tolerable | D9: KPI técnico
A10: Horas planificadas tesista | B10: 360 | C10: Total horas académicas planificadas | D10: Esfuerzo
A11: Horas ejecutadas actuales | B11: 70 | C11: Horas de trabajo académico actuales | D11: Esfuerzo
A12: Tarifa académica USD/h | B12: 8 | C12: Valorización estimada por hora | D12: Esfuerzo
A13: Costo académico planificado | B13: 2880 | C13: 360 h × USD 8/h | D13: Esfuerzo
A14: Costo académico ejecutado | B14: 560 | C14: 70 h × USD 8/h | D14: Esfuerzo
A15: Costo académico pendiente | B15: 2320 | C15: Horas restantes × USD 8/h | D15: Esfuerzo
A16: % esfuerzo ejecutado | B16: 0.1944 | C16: 70/360 = 19,44% | D16: Esfuerzo

Sheet Cronograma
A1: ID | B1: Fase | C1: Inicio | D1: Fin | E1: Días | F1: Avance actual | G1: Avance objetivo | H1: Estado | I1: Ruta crítica | J1: Hito
A2: F1 | B2: Inicio y alcance | C2: 46083 | D2: 46108 | E2: =D2-C2+1 -> 26 | F2: 1 | G2: 1 | H2: =IF(F2>=G2,"Finalizado",IF(F2>=0.7,"En curso","Atrasado")) -> Finalizado | I2: Sí | J2: H1 - Alcance definido
A3: F2 | B3: Revisión bibliográfica y normativa | C3: 46111 | D3: 46136 | E3: =D3-C3+1 -> 26 | F3: 1 | G3: 1 | H3: =IF(F3>=G3,"Finalizado",IF(F3>=0.7,"En curso","Atrasado")) -> Finalizado | I3: Sí | J3: H2 - Marco conceptual validado
A4: F3 | B4: Relevamiento y requerimientos | C4: 46139 | D4: 46171 | E4: =D4-C4+1 -> 33 | F4: 0.9 | G4: 1 | H4: =IF(F4>=G4,"Finalizado",IF(F4>=0.7,"En curso","Atrasado")) -> En curso | I4: Sí | J4: H3 - Requerimientos cerrados
A5: F4 | B5: Diseño técnico GPON | C5: 46174 | D5: 46262 | E5: =D5-C5+1 -> 89 | F5: 0.45 | G5: 1 | H5: =IF(F5>=G5,"Finalizado",IF(F5>=0.7,"En curso","Atrasado")) -> Atrasado | I5: Sí | J5: H4 - Diseño GPON validado
A6: F5 | B6: Análisis financiero e impacto | C6: 46188 | D6: 46276 | E6: =D6-C6+1 -> 89 | F6: 0.35 | G6: 1 | H6: =IF(F6>=G6,"Finalizado",IF(F6>=0.7,"En curso","Atrasado")) -> Atrasado | I6: No | J6: H5 - Modelo financiero comparado
A7: F6 | B7: Gestión, riesgos, Gantt, PERT y dashboard | C7: 46279 | D7: 46325 | E7: =D7-C7+1 -> 47 | F7: 0.15 | G7: 1 | H7: =IF(F7>=G7,"Finalizado",IF(F7>=0.7,"En curso","Atrasado")) -> Atrasado | I7: Sí | J7: H6 - Dashboard operativo
A8: F7 | B8: Redacción, revisión y defensa | C8: 46328 | D8: 46356 | E8: =D8-C8+1 -> 29 | F8: 0.05 | G8: 1 | H8: =IF(F8>=G8,"Finalizado",IF(F8>=0.7,"En curso","Atrasado")) -> Atrasado | I8: Sí | J8: H7 - Defensa final

Sheet KPIs
A1: ID | B1: KPI | C1: Objetivo | D1: Actual | E1: Meta | F1: Unidad | G1: Tipo | H1: Estado | I1: Normalizado % | J1: Interpretación
A2: KPI-01 | B2: Avance de redacción | C2: Páginas redact./planif. | D2: 0.45 | E2: 0.85 | F2: % | G2: Mayor es mejor | H2: =IF(G2="Mayor es mejor",IF(D2>=E2,"Verde",IF(D2>=E2*0.8,"Amarillo","Rojo")),IF(D2<=E2,"Verde",IF(D2<=E2*1.33,"Amarillo","Rojo"))) -> Rojo | I2: =IF(G2="Mayor es mejor",IF(E2=0,0,D2/E2),IF(D2=0,0,E2/D2)) -> 0.52941176 | J2: ≥85% OK; 70-84% Advertencia; <70% Crítico
A3: KPI-02 | B3: Cumplimiento cronograma | C3: Tareas a tiempo/planif. | D3: 0.8 | E3: 0.85 | F3: % | G3: Mayor es mejor | H3: =IF(G3="Mayor es mejor",IF(D3>=E3,"Verde",IF(D3>=E3*0.8,"Amarillo","Rojo")),IF(D3<=E3,"Verde",IF(D3<=E3*1.33,"Amarillo","Rojo"))) -> Amarillo | I3: =IF(G3="Mayor es mejor",IF(E3=0,0,D3/E3),IF(D3=0,0,E3/D3)) -> 0.94117647 | J3: ≥85% OK; 70-84% Advertencia; <70% Crítico
A4: KPI-03 | B4: Riesgos críticos abiertos | C4: Cant. riesgos rojos | D4: 2 | E4: 3 | F4: riesgos | G4: Menor es mejor | H4: =IF(G4="Mayor es mejor",IF(D4>=E4,"Verde",IF(D4>=E4*0.8,"Amarillo","Rojo")),IF(D4<=E4,"Verde",IF(D4<=E4*1.33,"Amarillo","Rojo"))) -> Verde | I4: =IF(G4="Mayor es mejor",IF(E4=0,0,D4/E4),IF(D4=0,0,E4/D4)) -> 1.5 | J4: ≤3 OK; 4-5 Advertencia; >5 Crítico
A5: KPI-04 | B5: Validación técnica | C5: Entregables valid./total | D5: 0.6 | E5: 1 | F5: % | G5: Mayor es mejor | H5: =IF(G5="Mayor es mejor",IF(D5>=E5,"Verde",IF(D5>=E5*0.8,"Amarillo","Rojo")),IF(D5<=E5,"Verde",IF(D5<=E5*1.33,"Amarillo","Rojo"))) -> Rojo | I5: =IF(G5="Mayor es mejor",IF(E5=0,0,D5/E5),IF(D5=0,0,E5/D5)) -> 0.6 | J5: 100% OK; 75-99% Advertencia; <75% Crítico
A6: KPI-05 | B6: Análisis financiero | C6: Escenarios resuel./req. | D6: 0.5 | E6: 1 | F6: % | G6: Mayor es mejor | H6: =IF(G6="Mayor es mejor",IF(D6>=E6,"Verde",IF(D6>=E6*0.8,"Amarillo","Rojo")),IF(D6<=E6,"Verde",IF(D6<=E6*1.33,"Amarillo","Rojo"))) -> Rojo | I6: =IF(G6="Mayor es mejor",IF(E6=0,0,D6/E6),IF(D6=0,0,E6/D6)) -> 0.5 | J6: 100% OK; 50-99% Advertencia; <50% Crítico
A7: KPI-06 | B7: Cobertura consignas | C7: Consignas resolv./total | D7: 0.8 | E7: 1 | F7: % | G7: Mayor es mejor | H7: =IF(G7="Mayor es mejor",IF(D7>=E7,"Verde",IF(D7>=E7*0.8,"Amarillo","Rojo")),IF(D7<=E7,"Verde",IF(D7<=E7*1.33,"Amarillo","Rojo"))) -> Amarillo | I7: =IF(G7="Mayor es mejor",IF(E7=0,0,D7/E7),IF(D7=0,0,E7/D7)) -> 0.8 | J7: 100% OK; 80-99% Advertencia; <80% Crítico
A8: KPI-07 | B8: Coherencia informe-dashboard | C8: Datos coinc./auditados | D8: 0.9 | E8: 0.98 | F8: % | G8: Mayor es mejor | H8: =IF(G8="Mayor es mejor",IF(D8>=E8,"Verde",IF(D8>=E8*0.8,"Amarillo","Rojo")),IF(D8<=E8,"Verde",IF(D8<=E8*1.33,"Amarillo","Rojo"))) -> Amarillo | I8: =IF(G8="Mayor es mejor",IF(E8=0,0,D8/E8),IF(D8=0,0,E8/D8)) -> 0.91836735 | J8: ≥98% OK; 90-97% Advertencia; <90% Crítico
A9: KPI-08 | B9: SLA con tutor | C9: Horas prom. respuesta | D9: 72 | E9: 72 | F9: horas | G9: Menor es mejor | H9: =IF(G9="Mayor es mejor",IF(D9>=E9,"Verde",IF(D9>=E9*0.8,"Amarillo","Rojo")),IF(D9<=E9,"Verde",IF(D9<=E9*1.33,"Amarillo","Rojo"))) -> Verde | I9: =IF(G9="Mayor es mejor",IF(E9=0,0,D9/E9),IF(D9=0,0,E9/D9)) -> 1 | J9: ≤72h OK; ≤96h Advertencia; >96h Crítico

Sheet Riesgos
A1: ID | B1: Riesgo | C1: Categoría | D1: Probabilidad | E1: Impacto | F1: Score | G1: Semáforo | H1: Plan preventivo | I1: Plan contingente | J1: Responsable | K1: Alerta temprana
A2: R1 | B2: Importación/falta stock OLT | C2: Proveedores | D2: 0.8 | E2: 3 | F2: =D2*E2 -> 2.4 | G2: =IF(F2>=1.8,"Rojo",IF(F2>=1,"Amarillo","Verde")) -> Rojo | H2: Vendors stock nac. | I2: Marca alt. o compra escalonada | J2: Área técnica | K2: Lead time >30 días
A3: R2 | B3: Tormentas eléctricas/humedad | C3: Entorno | D3: 0.8 | E3: 2 | F3: =D3*E3 -> 1.6 | G3: =IF(F3>=1.8,"Rojo",IF(F3>=1,"Amarillo","Verde")) -> Amarillo | H3: Cable ADSS, IP65 | I3: Reemplazo pasivos | J3: Mantenimiento | K3: Fallas post tormenta
A4: R3 | B4: Permisos postación EMSA/TVC5 | C4: Regulatorio | D4: 0.7 | E4: 2 | F4: =D4*E4 -> 1.4 | G4: =IF(F4>=1.8,"Rojo",IF(F4>=1,"Amarillo","Verde")) -> Amarillo | H4: Gestión temprana | I4: IRU/fibra oscura | J4: Municipio | K4: Sin respuesta formal
A5: R4 | B5: Vandalismo/cortes fibra | C5: Seguridad | D5: 0.6 | E5: 3 | F5: =D5*E5 -> 1.8 | G5: =IF(F5>=1.8,"Rojo",IF(F5>=1,"Amarillo","Verde")) -> Rojo | H5: Gabinetes prot. | I5: Reparación prioritaria | J5: NOC/Seguridad | K5: Enlace caído
A6: R5 | B6: Déficit técnicos GPON locales | C6: Soporte | D6: 0.6 | E6: 2 | F6: =D6*E6 -> 1.2 | G6: =IF(F6>=1.8,"Rojo",IF(F6>=1,"Amarillo","Verde")) -> Amarillo | H6: Capacitación CAPEX | I6: Cuadrilla ext. SLA | J6: Municipio | K6: Errores empalme
A7: R6 | B7: Cambio requisitos municipales | C7: Alcance | D7: 0.5 | E7: 2 | F7: =D7*E7 -> 1 | G7: =IF(F7>=1.8,"Rojo",IF(F7>=1,"Amarillo","Verde")) -> Amarillo | H7: Congelar alcance E1 | I7: Posponer a fase futura | J7: Tesista/Tutor | K7: Pedidos fuera alcance
A8: R7 | B8: Retrasos presupuestarios | C8: Presupuesto | D8: 0.4 | E8: 3 | F8: =D8*E8 -> 1.2 | G8: =IF(F8>=1.8,"Rojo",IF(F8>=1,"Amarillo","Verde")) -> Amarillo | H8: Ejecución por fases | I8: Fase mínima viable | J8: Municipio/Pcia | K8: Partidas no aprobadas
A9: R8 | B9: Cambio político | C9: Institucional | D9: 0.35 | E9: 3 | F9: =D9*E9 -> 1.05 | G9: =IF(F9>=1.8,"Rojo",IF(F9>=1,"Amarillo","Verde")) -> Amarillo | H9: Documentar impacto | I9: Reformular como seg. urbana | J9: Sponsor inst. | K9: Cambio de agenda
A10: R9 | B10: Sobrecostos de materiales | C10: Financiero | D10: 0.55 | E10: 2 | F10: =D10*E10 -> 1.1 | G10: =IF(F10>=1.8,"Rojo",IF(F10>=1,"Amarillo","Verde")) -> Amarillo | H10: Contingencia 10% | I10: Reducir fase 2 | J10: Compras/Tesista | K10: Cotizaciones +10%
A11: R10 | B11: Inconsistencia informe-dashboard | C11: Gestión acad. | D11: 0.45 | E11: 2 | F11: =D11*E11 -> 0.9 | G11: =IF(F11>=1.8,"Rojo",IF(F11>=1,"Amarillo","Verde")) -> Verde | H11: Congelar y auditar | I11: Corregir y registrar cambio | J11: Tesista | K11: Dif. CAPEX/VAN/TIR

Sheet Presupuesto
A1: Concepto | B1: Planificado / Estimado (USD) | C1: Ejecutado Real (USD) | D1: Pendiente (USD) | E1: % Ejecutado | F1: Tipo | G1: Escenario | H1: Comentario
A2: CAPEX infraestructura GPON | B2: 120730.72 | C2: 0 | D2: =IF(ISNUMBER(C2),B2-C2,"No aplica") -> 120730.72 | E2: =IF(OR(C2="No aplica",B2=0),"No aplica",C2/B2) -> 0 | F2: Infraestructura | G2: Ambos | H2: Inversión estimada: OLT, cámaras, ONT/ONU, NAP, fibra, instalación e ingeniería. No ejecutado físicamente.
A3: OPEX Año 1 | B3: 31325.58 | C3: 0 | D3: =IF(ISNUMBER(C3),B3-C3,"No aplica") -> 31325.58 | E3: =IF(OR(C3="No aplica",B3=0),"No aplica",C3/B3) -> 0 | F3: Operación | G3: Ambos | H3: Operación anual estimada: soporte, energía, postación, licencias, mantenimiento y conectividad.
A4: Esfuerzo académico del tesista | B4: 2880 | C4: 560 | D4: =IF(ISNUMBER(C4),B4-C4,"No aplica") -> 2320 | E4: =IF(OR(C4="No aplica",B4=0),"No aplica",C4/B4) -> 0.19444444 | F4: Recurso humano académico | G4: Académico | H4: Valorización del tiempo: 360 h planif. / 70 h actuales × USD 8/h. No es desembolso estatal.
A5: Beneficios sociales Año 1 | B5: 93360 | C5: No aplica | D5: =IF(ISNUMBER(C5),B5-C5,"No aplica") -> No aplica | E5: =IF(OR(C5="No aplica",B5=0),"No aplica",C5/B5) -> No aplica | F5: Beneficio social estimado | G5: Social | H5: Beneficio socioeconómico monetizado. No es gasto ni ingreso comercial ejecutado.
A6: VAN socioeconómico | B6: 90175.2 | C6: No aplica | D6: =IF(ISNUMBER(C6),B6-C6,"No aplica") -> No aplica | E6: =IF(OR(C6="No aplica",B6=0),"No aplica",C6/B6) -> No aplica | F6: Indicador financiero | G6: Social | H6: Indicador de viabilidad socioeconómica. No se grafica como presupuesto.
A7: VAN estatal | B7: -239413.53 | C7: No aplica | D7: =IF(ISNUMBER(C7),B7-C7,"No aplica") -> No aplica | E7: =IF(OR(C7="No aplica",B7=0),"No aplica",C7/B7) -> No aplica | F7: Indicador financiero | G7: Estatal | H7: Resultado financiero negativo. Defendible como política pública, no como inversión recuperable.
A8: Necesidad presupuestaria 5 años | B8: 299115.53 | C8: 0 | D8: =IF(ISNUMBER(C8),B8-C8,"No aplica") -> 299115.53 | E8: =IF(OR(C8="No aplica",B8=0),"No aplica",C8/B8) -> 0 | F8: Presupuesto público proyectado | G8: Estatal | H8: Necesidad total estimada para implementación y operación a 5 años. No ejecutada.

Sheet Alertas
A1: ID | B1: Alerta / Cuello de botella | C1: Severidad | D1: Origen | E1: Acción requerida | F1: Responsable | G1: Estado
A2: A1 | B2: Validar permisos de postación EMSA/TVC5 | C2: Alta | D2: R3 | E2: Solicitar respuesta formal y rutas alternativas | F2: Municipio | G2: Abierta
A3: A2 | B3: Confirmar stock OLT/switches y equivalentes | C3: Alta | D3: R1 | E3: Cotizar con al menos dos vendors | F3: Área técnica | G3: Abierta
A4: A3 | B4: Auditar coherencia CAPEX/OPEX/VAN entre documentos | C4: Media | D4: R10 | E4: Congelar versión y revisar valores clave | F4: Tesista | G4: Abierta
A5: A4 | B5: Cerrar diseño técnico GPON antes de integración financiera | C5: Alta | D5: Ruta crítica | E5: Validar topología y memoria técnica | F5: Tesista | G5: En curso
A6: A5 | B6: Actualizar progreso semanal del Gantt | C6: Media | D6: Dashboard | E6: Registrar avance por fase | F6: Tesista | G6: En curso
