Workbook

Sheet 00 Dashboard
A1: Rentabilidad socioeconomica - Proyecto TESIS GPON
A2: Escenario original rearmado con beneficios sociales monetizados
A4: Indicador | B4: Valor | C4: Unidad | D4: Lectura | F4: Conclusion para presentacion
A5: CAPEX inicial | B5: ='01 Supuestos'!C11 -> 120730.72 | C5: USD | D5: Inversion inicial total del proyecto | F5: El escenario estatal puro no recupera la inversion porque no carga ingresos directos. Al monetizar beneficios sociales, el proyecto pasa a ser viable socioeconomicamente. El beneficio social requerido para VAN = 0 es menor al beneficio base estimado. La rentabilidad no proviene de vender Internet, sino de seguridad, ahorro operativo y reutilizacion de la red.
A6: Beneficio social Ano 1 | B6: ='02 Beneficios'!G10 -> 93360 | C6: USD | D6: Beneficios monetizados por seguridad, ahorro y reutilizacion
A7: OPEX Ano 1 | B7: =-'03 EERR'!B6 -> 31325.575 | C7: USD | D7: Costo de operacion del primer ano
A8: Flujo libre Ano 1 | B8: ='04 EFE'!C11 -> 59619.81 | C8: USD | D8: Beneficio menos OPEX y reposiciones
A9: VAN socioeconomico | B9: ='05 Sensibilidad'!I15 -> 90175.196 | C9: USD | D9: Positivo con tasa de descuento del 15%
A10: TIR socioeconomica | B10: ='05 Sensibilidad'!J15 -> 0.42806785 | C10: % | D10: Retorno implicito del flujo social
A11: Payback simple | B11: ='05 Sensibilidad'!K15 -> 1.9939829 | C11: años | D11: Recupero estimado de la inversion
A12: Necesidad minima beneficio Año 1 | B12: ='05 Sensibilidad'!C5 -> 67816.783 | C12: USD | D12: Punto de equilibrio para VAN = 0
A13: Margen sobre equilibrio | B13: ='05 Sensibilidad'!C7 -> 0.37665037 | C13: % | D13: Diferencia entre beneficios base y minimo requerido
A16: Categoria beneficio | B16: Año 1 USD | C16: Participacion | F16: Flujo | G16: Año 0 | H16: Año 1 | I16: Año 2 | J16: Año 3 | K16: Año 4 | L16: Año 5
A17: ='02 Beneficios'!A5 -> Prevencion de incidentes | B17: ='02 Beneficios'!G5 -> 46240 | C17: =B17/SUM($B$17:$B$21) -> 0.49528706 | F17: Flujo libre | G17: ='04 EFE'!B11 -> -120730.72 | H17: ='04 EFE'!C11 -> 59619.81 | I17: ='04 EFE'!D11 -> 61480.843 | J17: ='04 EFE'!E11 -> 63397.707 | K17: ='04 EFE'!F11 -> 65372.077 | L17: ='04 EFE'!G11 -> 67405.677
A18: ='02 Beneficios'!A6 -> Respuesta temprana | B18: ='02 Beneficios'!G6 -> 12800 | C18: =B18/SUM($B$17:$B$21) -> 0.13710368 | F18: Flujo acumulado | G18: ='04 EFE'!B12 -> -120730.72 | H18: ='04 EFE'!C12 -> -61110.91 | I18: ='04 EFE'!D12 -> 369.93354 | J18: ='04 EFE'!E12 -> 63767.64 | K18: ='04 EFE'!F12 -> 129139.72 | L18: ='04 EFE'!G12 -> 196545.39
A19: ='02 Beneficios'!A7 -> Eficiencia investigacion | B19: ='02 Beneficios'!G7 -> 6240 | C19: =B19/SUM($B$17:$B$21) -> 0.066838046
A20: ='02 Beneficios'!A8 -> Ahorro conectividad | B20: ='02 Beneficios'!G8 -> 20160 | C20: =B20/SUM($B$17:$B$21) -> 0.2159383
A21: ='02 Beneficios'!A9 -> Reuso red municipal | B21: ='02 Beneficios'!G9 -> 7920 | C21: =B21/SUM($B$17:$B$21) -> 0.084832905

Sheet 01 Supuestos
A1: Supuestos del escenario socioeconomico
A2: Inputs editables para cuantificar beneficios sociales y recuperar la inversion
A4: Categoria | B4: Concepto | C4: Valor | D4: Unidad | E4: Tipo | F4: Fuente / criterio | G4: Notas
A5: Tecnico | B5: Cantidad de camaras | C5: 48 | D5: unid | E5: Input | F5: Tesis GPON / dimensionamiento preliminar | G5: Puntos de videovigilancia del modelo base
A6: Tecnico | B6: ONT/ONU por camara | C6: 1 | D6: unid | E6: Input | F6: Criterio tecnico | G6: Una terminal por punto de camara
A7: Tecnico | B7: Cajas NAP 1x8 | C7: 8 | D7: unid | E7: Input | F7: Topologia preliminar | G7: Capacidad total 64 puertos
A8: Tecnico | B8: OLT GPON | C8: 1 | D8: unid | E8: Input | F8: Arquitectura GPON | G8: OLT compacta de 8 puertos
A9: Tecnico | B9: Fibra total con reserva | C9: 29.716 | D9: km | E9: Input | F9: Calculo topologico | G9: Incluye feeder, distribucion, drops y reserva
A10: Tecnico | B10: Postes / apoyos estimados | C10: 593 | D10: unid | E10: Input | F10: Calculo topologico | G10: Ruta aerea con separacion promedio
A11: Financiero | B11: CAPEX inicial | C11: 120730.72 | D11: USD | E11: Input | F11: Modelo financiero previo | G11: Inversion inicial total con contingencia 10%
A12: Financiero | B12: OPEX Ano 1 | C12: 31325.575 | D12: USD | E12: Input | F12: Modelo financiero previo | G12: Operacion, soporte, energia, canon, licencias y repuestos
A13: Financiero | B13: Crecimiento anual OPEX | C13: 0.03 | D13: % | E13: Input | F13: Supuesto conservador | G13: Actualizacion anual en USD constantes
A14: Financiero | B14: Reposicion menor anual | C14: 0.02 | D14: % CAPEX | E14: Input | F14: Supuesto tecnico | G14: Reposiciones menores por desgaste, vandalismo o fallas
A15: Financiero | B15: Depreciacion anual | C15: 12560.853 | D15: USD | E15: Input | F15: Vida util tecnica | G15: Activos tecnologicos, pasivos ODN y software
A16: Financiero | B16: Tasa de descuento | C16: 0.15 | D16: % | E16: Input | F16: PPT finanzas / costo oportunidad | G16: Usada para descontar flujos futuros
... A19: Social | B19: Efectividad CCTV en reduccion de incidentes | C19: 0.16 | D19: % | E19: Input | F19: OJP / meta-analisis Welsh y Farrington | G19: Se usa 16% como escenario base sobre incidentes evitables

Sheet 02 Beneficios
A1: Beneficios sociales monetizados
A2: Escenario base para transformar la evaluacion estatal en evaluacion socioeconomica
A4: Categoria | B4: Variable 1 | C4: Cantidad | D4: Variable 2 | E4: Valor unitario USD | F4: Factor | G4: Beneficio Ano 1 USD | H4: Formula / logica | I4: Fuente / criterio | J4: Notas
A5: Prevencion de incidentes | B5: Incidentes evitables/año en zonas monitoreadas | C5: 170 | D5: Costo social promedio por incidente | E5: 1700 | F5: ='01 Supuestos'!C19 -> 0.16 | G5: =C5*E5*F5 -> 46240 | H5: Incidentes * costo social * efecto CCTV | I5: OJP + supuesto municipal a validar | J5: Incluye delitos menores, vandalismo, perdidas patrimoniales y costos de respuesta
A6: Respuesta temprana | B6: Eventos criticos con respuesta mas rapida/año | C6: 40 | D6: Costo evitado por no escalamiento | E6: 320 | F6: 1 | G6: =C6*E6*F6 -> 12800 | H6: Eventos * costo evitado | I6: Supuesto operativo | J6: Menor dano, menor movilizacion y mejor coordinacion de recursos
A7: Eficiencia investigacion | B7: Horas administrativas/policiales evitadas/año | C7: 520 | D7: Costo hora operativo | E7: 12 | F7: 1 | G7: =C7*E7*F7 -> 6240 | H7: Horas * costo hora | I7: Supuesto operativo | J7: Evidencia audiovisual reduce tiempo de busqueda y reconstruccion
A8: Ahorro conectividad | B8: Camaras que no requieren enlace comercial | C8: ='01 Supuestos'!C5 -> 48 | D8: Costo mensual enlace por camara | E8: 35 | F8: 12 | G8: =C8*E8*F8 -> 20160 | H8: Camaras * costo mensual * 12 | I8: Alternativa de leasing ISP | J8: Ahorro respecto de contratar enlaces individuales de datos
A9: Reuso red municipal | B9: Dependencias/servicios reutilizando la ODN | C9: 12 | D9: Valor mensual equivalente por punto | E9: 55 | F9: 12 | G9: =C9*E9*F9 -> 7920 | H9: Puntos * valor mensual * 12 | I9: Valor sombra de infraestructura | J9: La red puede soportar futuro IoT, puntos municipales y servicios de seguridad
A10: TOTAL | G10: =SUM(G5:G9) -> 93360

Sheet 03 EERR
A1: Estado de Resultados socioeconomico
A2: Criterio devengado: reconoce beneficios sociales como ingresos/beneficios economicos
A4: Concepto | B4: Año 1 | C4: Año 2 | D4: Año 3 | E4: Año 4 | F4: Año 5
A5: Beneficios sociales monetizados | B5: ='02 Beneficios'!G10 -> 93360 | C5: =B5*(1+'01 Supuestos'!$C$18) -> 96160.8 | D5: =C5*(1+'01 Supuestos'!$C$18) -> 99045.624 | E5: =D5*(1+'01 Supuestos'!$C$18) -> 102016.99 | F5: =E5*(1+'01 Supuestos'!$C$18) -> 105077.5
A6: OPEX | B6: =-'01 Supuestos'!$C$12 -> -31325.575 | C6: =B6*(1+'01 Supuestos'!$C$13) -> -32265.342 | D6: =C6*(1+'01 Supuestos'!$C$13) -> -33233.303 | E6: =D6*(1+'01 Supuestos'!$C$13) -> -34230.302 | F6: =E6*(1+'01 Supuestos'!$C$13) -> -35257.211
A7: EBITDA social | B7: =B5+B6 -> 62034.425 | C7: =C5+C6 -> 63895.458 | D7: =D5+D6 -> 65812.321 | E7: =E5+E6 -> 67786.691 | F7: =F5+F6 -> 69820.292
A8: Depreciacion | B8: =-'01 Supuestos'!$C$15 -> -12560.853 | C8: =-'01 Supuestos'!$C$15 -> -12560.853 | D8: =-'01 Supuestos'!$C$15 -> -12560.853 | E8: =-'01 Supuestos'!$C$15 -> -12560.853 | F8: =-'01 Supuestos'!$C$15 -> -12560.853
A9: EBIT / resultado operativo social | B9: =B7+B8 -> 49473.571 | C9: =C7+C8 -> 51334.604 | D9: =D7+D8 -> 53251.468 | E9: =E7+E8 -> 55225.838 | F9: =F7+F8 -> 57259.438
A10: Impuesto | B10: =IF(B9>0,-B9*'01 Supuestos'!$C$17,0) -> 0 | C10: =IF(C9>0,-C9*'01 Supuestos'!$C$17,0) -> 0 | D10: =IF(D9>0,-D9*'01 Supuestos'!$C$17,0) -> 0 | E10: =IF(E9>0,-E9*'01 Supuestos'!$C$17,0) -> 0 | F10: =IF(F9>0,-F9*'01 Supuestos'!$C$17,0) -> 0
A11: Resultado neto social | B11: =B9+B10 -> 49473.571 | C11: =C9+C10 -> 51334.604 | D11: =D9+D10 -> 53251.468 | E11: =E9+E10 -> 55225.838 | F11: =F9+F10 -> 57259.438

Sheet 04 EFE
A1: Estado de Flujo de Efectivo / Cash Flow socioeconomico
A2: Flujo libre antes de financiacion, con beneficios sociales monetizados
A4: Concepto | B4: Año 0 | C4: Año 1 | D4: Año 2 | E4: Año 3 | F4: Año 4 | G4: Año 5
A5: Beneficios sociales cobrados / valorados | B5: 0 | C5: ='03 EERR'!B5 -> 93360 | D5: ='03 EERR'!C5 -> 96160.8 | E5: ='03 EERR'!D5 -> 99045.624 | F5: ='03 EERR'!E5 -> 102016.99 | G5: ='03 EERR'!F5 -> 105077.5
A6: Pagos operativos OPEX | B6: 0 | C6: ='03 EERR'!B6 -> -31325.575 | D6: ='03 EERR'!C6 -> -32265.342 | E6: ='03 EERR'!D6 -> -33233.303 | F6: ='03 EERR'!E6 -> -34230.302 | G6: ='03 EERR'!F6 -> -35257.211
A7: Flujo neto operativo | B7: 0 | C7: =C5+C6 -> 62034.425 | D7: =D5+D6 -> 63895.458 | E7: =E5+E6 -> 65812.321 | F7: =F5+F6 -> 67786.691 | G7: =G5+G6 -> 69820.292
A8: CAPEX inicial | B8: =-'01 Supuestos'!$C$11 -> -120730.72 | C8: 0 | D8: 0 | E8: 0 | F8: 0 | G8: 0
A9: CAPEX reposicion menor | B9: 0 | C9: =-'01 Supuestos'!$C$11*'01 Supuestos'!$C$14 -> -2414.6144 | D9: =-'01 Supuestos'!$C$11*'01 Supuestos'!$C$14 -> -2414.6144 | E9: =-'01 Supuestos'!$C$11*'01 Supuestos'!$C$14 -> -2414.6144 | F9: =-'01 Supuestos'!$C$11*'01 Supuestos'!$C$14 -> -2414.6144 | G9: =-'01 Supuestos'!$C$11*'01 Supuestos'!$C$14 -> -2414.6144
A10: Flujo neto de inversion | B10: =B8+B9 -> -120730.72 | C10: =C8+C9 -> -2414.6144 | D10: =D8+D9 -> -2414.6144 | E10: =E8+E9 -> -2414.6144 | F10: =F8+F9 -> -2414.6144 | G10: =G8+G9 -> -2414.6144
A11: Flujo libre antes de financiacion | B11: =B7+B10 -> -120730.72 | C11: =C7+C10 -> 59619.81 | D11: =D7+D10 -> 61480.843 | E11: =E7+E10 -> 63397.707 | F11: =F7+F10 -> 65372.077 | G11: =G7+G10 -> 67405.677
A12: Flujo acumulado | B12: =B11 -> -120730.72 | C12: =B12+C11 -> -61110.91 | D12: =C12+D11 -> 369.93354 | E12: =D12+E11 -> 63767.64 | F12: =E12+F11 -> 129139.72 | G12: =F12+G11 -> 196545.39

Sheet 05 Sensibilidad
A1: Sensibilidad VAN / TIR
A2: Cuanto beneficio social anual se necesita para que el proyecto recupere la inversion
A4: Indicador | B4: Formula / criterio | C4: Valor | D4: Unidad | F4: Auxiliar | G4: Valor
A5: Beneficio social Ano 1 minimo para VAN = 0 | B5: Calculado con crecimiento anual de beneficios del 3% | C5: =-G6/G5 -> 67816.783 | D5: USD | F5: PV factor beneficios crecientes | G5: =SUM(1/(1+'01 Supuestos'!$C$16),(1+'01 Supuestos'!$C$18)/(1+'01 Supuestos'!$C$16)^2,(1+'01 Supuestos'!$C$18)^2/(1+'01 Supuestos'!$C$16)^3,(1+'01 Supuestos'!$C$18)^3/(1+'01 Supuestos'!$C$16)^4,(1+'01 Supuestos'!$C$18)^4/(1+'01 Supuestos'!$C$16)^5) -> 3.5302992
A6: Beneficio social Ano 1 escenario base | B6: Suma de categorias monetizadas | C6: ='02 Beneficios'!G10 -> 93360 | D6: USD | F6: VAN base sin beneficios | G6: {='04 EFE'!B11+NPV('01 Supuestos'!$C$16,'04 EFE'!C6+'04 EFE'!C9,'04 EFE'!D6+'04 EFE'!D9,'04 EFE'!E6+'04 EFE'!E9,'04 EFE'!F6+'04 EFE'!F9,'04 EFE'!G6+'04 EFE'!G9)} -> -239413.53
A7: Margen sobre punto de equilibrio | B7: Beneficio base / beneficio minimo - 1 | C7: =C6/C5-1 -> 0.37665037 | D7: % | F7: Tasa descuento | G7: ='01 Supuestos'!$C$16 -> 0.15
A8: Beneficio mensual equivalente por camara - equilibrio | B8: Beneficio minimo / 48 camaras / 12 meses | C8: =C5/G9/12 -> 117.73747 | D8: USD/camara/mes | F8: Crecimiento beneficios | G8: ='01 Supuestos'!$C$18 -> 0.03
A9: Beneficio mensual equivalente por camara - base | B9: Beneficio base / 48 camaras / 12 meses | C9: =C6/G9/12 -> 162.08333 | D9: USD/camara/mes | F9: Camaras | G9: ='01 Supuestos'!$C$5 -> 48
A12: Escenario | B12: Beneficio Ano 1 | C12: Año 0 | D12: Año 1 | E12: Año 2 | F12: Año 3 | G12: Año 4 | H12: Año 5 | I12: VAN | J12: TIR | K12: Payback simple
A13: Equilibrio | B13: =$C$5 -> 67816.783 | C13: =-'01 Supuestos'!$C$11 -> -120730.72 | D13: =$B13*(1+'01 Supuestos'!$C$18)^0-'01 Supuestos'!$C$12*(1+'01 Supuestos'!$C$13)^0-'01 Supuestos'!$C$11*'01 Supuestos'!$C$14 -> 34076.594 | E13: =$B13*(1+'01 Supuestos'!$C$18)^1-'01 Supuestos'!$C$12*(1+'01 Supuestos'!$C$13)^1-'01 Supuestos'!$C$11*'01 Supuestos'!$C$14 -> 35171.33 | F13: =$B13*(1+'01 Supuestos'!$C$18)^2-'01 Supuestos'!$C$12*(1+'01 Supuestos'!$C$13)^2-'01 Supuestos'!$C$11*'01 Supuestos'!$C$14 -> 36298.908 | G13: =$B13*(1+'01 Supuestos'!$C$18)^3-'01 Supuestos'!$C$12*(1+'01 Supuestos'!$C$13)^3-'01 Supuestos'!$C$11*'01 Supuestos'!$C$14 -> 37460.314 | H13: =$B13*(1+'01 Supuestos'!$C$18)^4-'01 Supuestos'!$C$12*(1+'01 Supuestos'!$C$13)^4-'01 Supuestos'!$C$11*'01 Supuestos'!$C$14 -> 38656.562 | I13: {=C13+NPV('01 Supuestos'!$C$16,D13:H13)} -> 0 | J13: =IRR(C13:H13) -> 0.15 | K13: 3.4053326
A14: Conservador | B14: 70000 | C14: =-'01 Supuestos'!$C$11 -> -120730.72 | D14: =$B14*(1+'01 Supuestos'!$C$18)^0-'01 Supuestos'!$C$12*(1+'01 Supuestos'!$C$13)^0-'01 Supuestos'!$C$11*'01 Supuestos'!$C$14 -> 36259.81 | E14: =$B14*(1+'01 Supuestos'!$C$18)^1-'01 Supuestos'!$C$12*(1+'01 Supuestos'!$C$13)^1-'01 Supuestos'!$C$11*'01 Supuestos'!$C$14 -> 37420.043 | F14: =$B14*(1+'01 Supuestos'!$C$18)^2-'01 Supuestos'!$C$12*(1+'01 Supuestos'!$C$13)^2-'01 Supuestos'!$C$11*'01 Supuestos'!$C$14 -> 38615.083 | G14: =$B14*(1+'01 Supuestos'!$C$18)^3-'01 Supuestos'!$C$12*(1+'01 Supuestos'!$C$13)^3-'01 Supuestos'!$C$11*'01 Supuestos'!$C$14 -> 39845.974 | H14: =$B14*(1+'01 Supuestos'!$C$18)^4-'01 Supuestos'!$C$12*(1+'01 Supuestos'!$C$13)^4-'01 Supuestos'!$C$11*'01 Supuestos'!$C$14 -> 41113.791 | I14: {=C14+NPV('01 Supuestos'!$C$16,D14:H14)} -> 7707.4078 | J14: =IRR(C14:H14) -> 0.17605381 | K14: 3.2117098
A15: Base socioeconomico | B15: =$C$6 -> 93360 | C15: =-'01 Supuestos'!$C$11 -> -120730.72 | D15: =$B15*(1+'01 Supuestos'!$C$18)^0-'01 Supuestos'!$C$12*(1+'01 Supuestos'!$C$13)^0-'01 Supuestos'!$C$11*'01 Supuestos'!$C$14 -> 59619.81 | E15: =$B15*(1+'01 Supuestos'!$C$18)^1-'01 Supuestos'!$C$12*(1+'01 Supuestos'!$C$13)^1-'01 Supuestos'!$C$11*'01 Supuestos'!$C$14 -> 61480.843 | F15: =$B15*(1+'01 Supuestos'!$C$18)^2-'01 Supuestos'!$C$12*(1+'01 Supuestos'!$C$13)^2-'01 Supuestos'!$C$11*'01 Supuestos'!$C$14 -> 63397.707 | G15: =$B15*(1+'01 Supuestos'!$C$18)^3-'01 Supuestos'!$C$12*(1+'01 Supuestos'!$C$13)^3-'01 Supuestos'!$C$11*'01 Supuestos'!$C$14 -> 65372.077 | H15: =$B15*(1+'01 Supuestos'!$C$18)^4-'01 Supuestos'!$C$12*(1+'01 Supuestos'!$C$13)^4-'01 Supuestos'!$C$11*'01 Supuestos'!$C$14 -> 67405.677 | I15: {=C15+NPV('01 Supuestos'!$C$16,D15:H15)} -> 90175.196 | J15: =IRR(C15:H15) -> 0.42806785 | K15: 1.9939829
A16: Alto impacto | B16: 115000 | C16: =-'01 Supuestos'!$C$11 -> -120730.72 | D16: =$B16*(1+'01 Supuestos'!$C$18)^0-'01 Supuestos'!$C$12*(1+'01 Supuestos'!$C$13)^0-'01 Supuestos'!$C$11*'01 Supuestos'!$C$14 -> 81259.81 | E16: =$B16*(1+'01 Supuestos'!$C$18)^1-'01 Supuestos'!$C$12*(1+'01 Supuestos'!$C$13)^1-'01 Supuestos'!$C$11*'01 Supuestos'!$C$14 -> 83770.043 | F16: =$B16*(1+'01 Supuestos'!$C$18)^2-'01 Supuestos'!$C$12*(1+'01 Supuestos'!$C$13)^2-'01 Supuestos'!$C$11*'01 Supuestos'!$C$14 -> 86355.583 | G16: =$B16*(1+'01 Supuestos'!$C$18)^3-'01 Supuestos'!$C$12*(1+'01 Supuestos'!$C$13)^3-'01 Supuestos'!$C$11*'01 Supuestos'!$C$14 -> 89018.689 | H16: =$B16*(1+'01 Supuestos'!$C$18)^4-'01 Supuestos'!$C$12*(1+'01 Supuestos'!$C$13)^4-'01 Supuestos'!$C$11*'01 Supuestos'!$C$14 -> 91761.688 | I16: {=C16+NPV('01 Supuestos'!$C$16,D16:H16)} -> 166570.87 | J16: =IRR(C16:H16) -> 0.63735472 | K16: 1.4711817

Sheet 07 Fuentes
A1: Fuentes, notas y advertencias metodologicas
A2: Usar estas notas para defender la cuantificacion de beneficios sociales
A4: Tipo | B4: Fuente / referencia | C4: Uso en el modelo | D4: URL / archivo | E4: Nota
A5: Archivo tesis | B5: UCP - TESIS GPON.pdf | C5: Contexto tecnico: FTTH/GPON, videovigilancia, alcance, PMBOK/Pressman, riesgos | D5: Archivo cargado en conversacion | E5: Base del proyecto
A6: Archivo finanzas | B6: Finanzas de un proyecto.pptx | C6: EERR por devengado, EFE/Cash Flow y valor tiempo del dinero | D6: Archivo cargado en conversacion | E6: Base financiera
A7: Evidencia CCTV | B7: Welsh & Farrington / OJP systematic review | C7: Sustenta uso de reduccion de incidentes como beneficio social | D7: https://ojp.gov/ncjrs/virtual-library/abstracts/public-area-cctv-and-crime-prevention-update-systematic-review-and | E7: Meta-analisis reporta disminucion modesta y significativa; se uso 16% como escenario base
A8: Evidencia CCTV actualizada | B8: Piza, Welsh, Farrington & Thomas / OJP 40-year review | C8: Soporte general de impacto de CCTV sobre reduccion de crimen | D8: https://www.ojp.gov/library/publications/cctv-surveillance-crime-prevention-40-year-systematic-review-meta-analysis | E8: Efectos mayores cuando hay monitoreo activo y objetivos concretos
A9: Supuesto municipal | B9: Valores de incidentes, costos y horas | C9: Cuantificar beneficios monetizados | D9: Debe validarse con municipio, policia o datos historicos | E9: Los montos no son cifras oficiales; son supuestos editables para escenario socioeconomico
