Workbook

Sheet 00 Resumen
A1: Analisis financiero - TESIS GPON Bernardo de Irigoyen
A2: Proyecto estatal de red FTTH/GPON para videovigilancia urbana
A3: KPI | B3: Valor | C3: Unidad | D3: Comentario
A4: CAPEX total inicial | B4: ='03 CAPEX'!$F$24 -> 121189.63 | C4: USD | D4: Inversion inicial estimada
A5: Fibra total con reserva | B5: ='02 Topologia'!$B$18 -> 29.716 | C5: km | D5: Incluye feeder, distribucion, drops y reserva tecnica
A6: Camaras | B6: ='01 Supuestos'!$C$4 -> 48 | C6: unid | D6: Puntos de videovigilancia
A7: Cajas NAP | B7: ='01 Supuestos'!$C$7 -> 8 | C7: unid | D7: Capacidad total 64 puertos
A8: ONT/ONU | B8: ='01 Supuestos'!$C$4*'01 Supuestos'!$C$5 -> 48 | C8: unid | D8: Una terminal por camara
A9: Postes / apoyos | B9: ='02 Topologia'!$B$20 -> 593 | C9: unid | D9: Apoyos estimados para ruta aerea
A10: OPEX Año 1 | B10: ='04 OPEX'!$C$11 -> 30956.034 | C10: USD | D10: Gasto operativo anual base
A11: Resultado neto Año 1 | B11: ='06 EERR'!$B$12 -> -47558.324 | C11: USD | D11: Contable, criterio devengado
A12: VAN flujo libre | B12: ='08 VAN TIR'!$B$9 -> -238598.61 | C12: USD | D12: Negativo en escenario estatal sin monetizar beneficios
A13: TIR flujo libre | B13: No aplica | C13: % | D13: No aplica porque todos los flujos libres son negativos
A14: Necesidad presupuestaria total | B14: ='08 VAN TIR'!$B$12 -> 297658.38 | C14: USD | D14: Implementacion + 5 anos de operacion

Sheet 01 Supuestos
A1: Supuestos del modelo
A2: Inputs tecnicos y financieros editables. Los valores hardcodeados estan en azul.
A3: Codigo | B3: Concepto | C3: Valor | D3: Unidad | E3: Tipo | F3: Fuente / criterio | G3: Notas
A4: T01 | B4: Cantidad de camaras IP | C4: 48 | D4: unid | E4: Input | F4: TESIS GPON + dimensionamiento por sectores criticos | G4: Modelo base de cobertura urbana y frontera seca
A5: T02 | B5: ONT / ONU por camara | C5: 1 | D5: unid | E5: Input | F5: Criterio tecnico | G5: Una ONT outdoor o ONU por punto de camara
A6: T03 | B6: Camaras promedio por NAP | C6: 6 | D6: unid | E6: Input | F6: Criterio tecnico | G6: Se deja capacidad libre para expansion
A7: T04 | B7: Cajas NAP 1x8 | C7: 8 | D7: unid | E7: Input | F7: T01/T03 redondeado + reserva | G7: 8 NAP x 8 salidas = 64 puertos posibles
A8: T05 | B8: Capacidad por NAP | C8: 8 | D8: puertos | E8: Input | F8: Splitter 1x8 | G8: Capacidad por caja NAP
A9: T06 | B9: OLT | C9: 1 | D9: unid | E9: Input | F9: Arquitectura GPON | G9: OLT compacta 8 puertos GPON
A10: T07 | B10: Puertos GPON en OLT | C10: 8 | D10: puertos | E10: Input | F10: Arquitectura GPON | G10: Un puerto por ramal/NAP en modelo preliminar
A11: T08 | B11: Fibra feeder / backbone | C11: 9.6 | D11: km | E11: Input | F11: Topologia conceptual | G11: Anillo/eje troncal preliminar
A12: T09 | B12: Fibra distribucion | C12: 12.4 | D12: km | E12: Input | F12: Topologia conceptual | G12: Ramas hacia sectores criticos
A13: T10 | B13: Drop promedio por camara | C13: 0.08 | D13: km | E13: Input | F13: Criterio de acometida | G13: 80 metros promedio por camara
A14: T11 | B14: Reserva tecnica de fibra | C14: 0.15 | D14: % | E14: Input | F14: Buenas practicas ODN | G14: Reserva por empalmes, slack y contingencia
A15: T12 | B15: Ruta aerea con postacion | C15: 22 | D15: km | E15: Input | F15: Feeder + distribucion | G15: Se asume uso de postacion existente donde sea posible
... A23: T20 | B23: Redundancia de discos | C23: 1.25 | D23: Factor | E23: input | F23: Criterio tecnico | G23: Agrega 25% de capacidad bruta (RAID)
A28: Codigo | B28: Concepto | C28: Valor | D28: Unidad | E28: Tipo | F28: Fuente / criterio | G28: Notas
A29: F01 | B29: Moneda del modelo | C29: USD constantes | D29: texto | E29: Input | F29: Criterio de modelado | G29: No incluye inflacion ni diferencia de cambio
A30: F02 | B30: Tasa de descuento | C30: 0.15 | D30: % | E30: Input | F30: PPT valor tiempo del dinero | G30: Usada para VAN
A31: F03 | B31: Impuesto a las ganancias | C31: 0 | D31: % | E31: Input | F31: Proyecto estatal | G31: No aplicable en escenario publico
A32: F04 | B32: Crecimiento anual OPEX | C32: 0.03 | D32: % | E32: Input | F32: Estimacion conservadora | G32: OPEX en USD constantes con leve actualizacion tecnica
A33: F05 | B33: Ingresos comerciales directos | C33: 0 | D33: USD/anual | E33: Input | F33: Proyecto estatal sin canon | G33: Base honesta: no monetiza ingresos
A34: F06 | B34: Beneficios monetizados | C34: 0 | D34: USD/anual | E34: Input | F34: No monetizado | G34: No se cargan ahorros/beneficios para forzar VAN
A35: F07 | B35: CAPEX de reposicion menor | C35: 0.02 | D35: % CAPEX | E35: Input | F35: Mantenimiento de activo fijo | G35: Reposiciones menores anuales desde Año 1
A36: F08 | B36: Vida util fibra y pasivos | C36: 10 | D36: años | E36: Input | F36: Criterio contable tecnico | G36: Depreciacion lineal
A37: F09 | B37: Vida util activos tecnologicos | C37: 5 | D37: años | E37: Input | F37: Criterio contable tecnico | G37: OLT, ONT, camaras, servidores
A38: F10 | B38: Vida util software/licencias | C38: 3 | D38: años | E38: Input | F38: Criterio contable tecnico | G38: VMS y configuracion inicial si capitalizable
A39: F11 | B39: Valor residual al Ano 5 | C39: 0 | D39: USD | E39: Input | F39: Conservador | G39: No se reconoce venta ni recupero al ano 5
A40: F12 | B40: Mantenimiento preventivo ODN | C40: 0.035 | D40: % CAPEX | E40: Input | F40: Estimación | G40: Aplica sobre capex total

Sheet 02 Topologia
A1: Topologia preliminar y dimensionamiento fisico
A2: Distribucion base de camaras, NAP, fibra y apoyos por sector
A3: Sector | B3: Criticidad | C3: Camaras | D3: ONT | E3: NAP | F3: Feeder km | G3: Distribucion km | H3: Drop km | I3: Fibra total km | J3: Postes / apoyos | K3: Observaciones
A4: Nodo central / municipio / centro de monitoreo | B4: Alta | C4: 0 | D4: 0 | E4: 0 | F4: 9.6 | G4: 0 | H4: 0 | I4: =SUM(F4:H4) -> 9.6 | J4: 259 | K4: Ubicacion de OLT, core, firewall/NVR y salida al centro de monitoreo
A5: Frontera seca y pasos criticos | B5: Muy alta | C5: 18 | D5: 18 | E5: 3 | F5: 0 | G5: 4.6 | H5: =C5*'01 Supuestos'!$C$13 -> 1.44 | I5: =SUM(F5:H5) -> 6.04 | J5: 124 | K5: Cobertura de zonas de alto transito e ingreso/egreso fronterizo
A6: Accesos principales y rutas | B6: Alta | C6: 10 | D6: 10 | E6: 2 | F6: 0 | G6: 3.2 | H6: =C6*'01 Supuestos'!$C$13 -> 0.8 | I6: =SUM(F6:H6) -> 4 | J6: 86 | K6: Monitoreo de entradas, salidas y corredores vehiculares
A7: Casco urbano y zona comercial | B7: Media alta | C7: 12 | D7: 12 | E7: 2 | F7: 0 | G7: 3 | H7: =C7*'01 Supuestos'!$C$13 -> 0.96 | I7: =SUM(F7:H7) -> 3.96 | J7: 81 | K7: Plazas, avenidas, puntos comerciales y circulacion peatonal
A8: Instituciones, plazas y servicios publicos | B8: Media | C8: 8 | D8: 8 | E8: 1 | F8: 0 | G8: 1.6 | H8: =C8*'01 Supuestos'!$C$13 -> 0.64 | I8: =SUM(F8:H8) -> 2.24 | J8: 43 | K8: Escuelas, salud, dependencias publicas y espacios de reunion
A9: TOTAL | C9: =SUM(C4:C8) -> 48 | D9: =SUM(D4:D8) -> 48 | E9: =SUM(E4:E8) -> 8 | F9: =SUM(F4:F8) -> 9.6 | G9: =SUM(G4:G8) -> 12.4 | H9: =SUM(H4:H8) -> 3.84 | I9: =SUM(I4:I8) -> 25.84 | J9: =SUM(J4:J8) -> 593
A13: Concepto | B13: Valor | C13: Unidad | D13: Formula / criterio
A14: Capacidad total de NAP | B14: ='01 Supuestos'!$C$7*'01 Supuestos'!$C$8 -> 64 | C14: puertos | D14: Cajas NAP x capacidad por NAP
A15: Puertos libres NAP | B15: =B14-'01 Supuestos'!$C$4 -> 16 | C15: puertos | D15: Capacidad total menos camaras
A16: Fibra total base | B16: =I9 -> 25.84 | C16: km | D16: Feeder + distribucion + drops
A17: Reserva tecnica fibra | B17: ='01 Supuestos'!$C$14 -> 0.15 | C17: % | D17: Slack, empalmes y contingencia
A18: Fibra total con reserva | B18: =B16*(1+B17) -> 29.716 | C18: km | D18: Fibra total base con reserva
A19: Ruta aerea con postacion | B19: ='01 Supuestos'!$C$15 -> 22 | C19: km | D19: Ruta aerea estimada
A20: Postes / apoyos estimados | B20: =J9 -> 593 | C20: unid | D20: Estimacion preliminar por tramos
A21: Postes nuevos estimados | B21: =ROUND(B20*'01 Supuestos'!$C$17,0) -> 30 | C21: unid | D21: 5% de apoyos
A22: Trafico promedio total | B22: ='01 Supuestos'!$C$4*'01 Supuestos'!$C$18 -> 288 | C22: Mbps | D22: Camaras x bitrate promedio
A23: Trafico pico total | B23: ='01 Supuestos'!$C$4*'01 Supuestos'!$C$19 -> 384 | C23: Mbps | D23: Camaras x bitrate pico
A24: Capacidad util upstream GPON por puerto | B24: ='01 Supuestos'!$C$21*1000*'01 Supuestos'!$C$20 -> 1119.6 | C24: Mbps | D24: Capacidad nominal x eficiencia
A25: Utilizacion GPON pico agregada | B25: =B23/(B24*'01 Supuestos'!$C$10) -> 0.042872454 | C25: % | D25: Trafico pico total / capacidad total de subida

Sheet 03 CAPEX
A1: CAPEX - Inversion inicial
A2: Equipamiento, planta externa, instalacion y contingencia tecnica. Financiado por el ministerio de Gobierno de la Provincia de Misiones.
A3: Categoria | B3: Item | C3: Cantidad | D3: Unidad | E3: Costo unitario USD | F3: Subtotal USD | G3: Vida util | H3: Tipo activo | I3: Fuente / criterio | J3: Notas
A4: Activo | B4: OLT GPON 8 puertos | C4: 1 | D4: unid | E4: 4500 | F4: =C4*E4 -> 4500 | G4: 5 | H4: Tecnologico | I4: Vendor tipo Huawei/ZTE compacto | J4: Equipo OLT base para 8 ramales GPON
A5: Activo | B5: Modulo SFP/optica GPON y repuestos | C5: 8 | D5: unid | E5: 85 | F5: =C5*E5 -> 680 | G5: 5 | H5: Tecnologico | I5: Criterio tecnico | J5: Opticas y repuestos minimos
A6: Activo | B6: Router/firewall perimetral | C6: 1 | D6: unid | E6: 1800 | F6: =C6*E6 -> 1800 | G6: 5 | H6: Tecnologico | I6: Firewall tipo Fortinet/Cisco | J6: Segmentacion de red, VPN, seguridad y ruteo inter-VLAN
A7: Activo | B7: Switch core/distribucion | C7: 1 | D7: unid | E7: 2200 | F7: =C7*E7 -> 2200 | G7: 5 | H7: Tecnologico | I7: Switch empresarial | J7: Conmutacion central para NOC y video
A8: Activo | B8: Servidor de grabación y licencias VMS | C8: 1 | D8: unid | E8: 3500 | F8: =C8*E8 -> 3500 | G8: 5 | H8: Software/servicio | I8: Grabacion de video | J8: Hardware base para VMS y gestión de video
A9: Activo | B9: Subsistema de almacenamiento | C9: =('01 Supuestos'!C4 * 6 * 30 * 10.8) / 1024 * 1.25 -> 113.90625 | D9: TB | E9: 30 | F9: =C9*E9 -> 3417.1875 | G9: ='01 Supuestos'!C37 -> 5 | H9: Tecnológico | I9: Cálculo por fórmula (30 días, RAID). | J9: Capacidad bruta en TB para retención operativa de evidencia
A10: Activo | B10: Camaras IP PoE 4MP/8MP IP66 | C10: ='01 Supuestos'!$C$4 -> 48 | D10: unid | E10: 220 | F10: =C10*E10 -> 10560 | G10: 5 | H10: Tecnologico | I10: Puntos de videovigilancia | J10: Camara, soporte y accesorios basicos
A11: Activo | B11: ONT/ONU GPON outdoor por camara | C11: ='01 Supuestos'!$C$4 -> 48 | D11: unid | E11: 65 | F11: =C11*E11 -> 3120 | G11: 5 | H11: Tecnologico | I11: Acceso GPON | J11: Terminal optica por punto
A12: Activo | B12: Gabinete, PoE, UPS menor por punto | C12: ='01 Supuestos'!$C$4 -> 48 | D12: unid | E12: 75 | F12: =C12*E12 -> 3600 | G12: 5 | H12: Tecnologico | I12: Planta externa camara | J12: Proteccion, energia y respaldo local basico
A13: Pasivo | B13: Cajas NAP 1x8 con splitter | C13: 8 | D13: unid | E13: 110 | F13: =C13*E13 -> 880 | G13: 10 | H13: Pasivo | I13: ODN | J13: CTO/NAP con divisor 1x8
A14: Pasivo | B14: Fibra ADSS total con reserva | C14: ='02 Topologia'!B18 -> 29.716 | D14: km | E14: 1200 | F14: =C14*E14 -> 35659.2 | G14: 10 | H14: Pasivo | I14: Cableado ADSS | J14: Incluye feeder, distribucion, drops y reserva tecnica
A15: Pasivo | B15: ODF, patchcords, bandejas y empalmes | C15: 1 | D15: lote | E15: 3200 | F15: =C15*E15 -> 3200 | G15: 10 | H15: Pasivo | I15: ODN | J15: Elementos de terminacion y fusion
A16: Pasivo | B16: Herrajes y materiales de postacion | C16: ='02 Topologia'!B20 -> 593 | D16: puntos | E16: 12 | F16: =C16*E16 -> 7116 | G16: 10 | H16: Pasivo | I16: Postacion compartida | J16: Morseteria, precintos, reserva y fijaciones
A17: Pasivo | B17: Postes nuevos estimados | C17: ='02 Topologia'!B21 -> 30 | D17: unid | E17: 150 | F17: =C17*E17 -> 4500 | G17: 10 | H17: Pasivo | I17: Allowance preliminar | J17: Solo 5% de apoyos como nuevos; resto compartido
A18: Servicio | B18: Mano de obra tendido y fusion | C18: ='01 Supuestos'!C15 -> 22 | D18: km | E18: 650 | F18: =C18*E18 -> 14300 | G18: 10 | H18: Servicio | I18: Instalacion ODN | J18: Tendido sobre ruta aerea estimada
A19: Servicio | B19: Instalacion y orientacion de camaras | C19: 48 | D19: unid | E19: 55 | F19: =C19*E19 -> 2640 | G19: 5 | H19: Servicio | I19: Implementacion | J19: Montaje, pruebas y puesta en servicio
A20: Servicio | B20: Configuracion GPON/NOC/VMS | C20: 1 | D20: lote | E20: 2500 | F20: =C20*E20 -> 2500 | G20: 3 | H20: Software/servicio | I20: Implementacion logica | J20: Provisionamiento OLT/ONT, VLAN, monitoreo y VMS
A21: Servicio | B21: Ingenieria, relevamiento y documentacion | C21: 1 | D21: lote | E21: 6000 | F21: =C21*E21 -> 6000 | G21: 3 | H21: Servicio | I21: Gestion de proyecto | J21: Planos, memoria tecnica y pruebas de aceptacion
A22: TOTAL | B22: Subtotal CAPEX directo | F22: =SUM(F4:F21) -> 110172.39
A23: TOTAL | B23: Contingencia tecnica 10% | F23: =F22*10% -> 11017.239
A24: TOTAL | B24: CAPEX total inicial | F24: =SUM(F22:F23) -> 121189.63

Sheet 04 OPEX
A1: OPEX - Gasto operativo proyectado
A2: USD constantes; crecimiento anual editable en Supuestos
A3: Concepto | B3: Base Ano 1 USD | C3: Año 1 | D3: Año 2 | E3: Año 3 | F3: Año 4 | G3: Año 5 | H3: Criterio
A4: Operacion NOC y soporte tecnico | B4: 12000 | C4: =B4 -> 12000 | D4: =C4*(1+'01 Supuestos'!$C$32) -> 12360 | E4: =D4*(1+'01 Supuestos'!$C$32) -> 12730.8 | F4: =E4*(1+'01 Supuestos'!$C$32) -> 13112.724 | G4: =F4*(1+'01 Supuestos'!$C$32) -> 13506.106 | H4: Personal/guardia compartida para monitoreo y mantenimiento
A5: Mantenimiento preventivo ODN | B5: ='03 CAPEX'!$F$22 * '01 Supuestos'!$C$40 -> 3856.0336 | C5: =B5 -> 3856.0336 | D5: =C5*(1+'01 Supuestos'!$C$32) -> 3971.7146 | E5: =D5*(1+'01 Supuestos'!$C$32) -> 4090.866 | F5: =E5*(1+'01 Supuestos'!$C$32) -> 4213.592 | G5: =F5*(1+'01 Supuestos'!$C$32) -> 4339.9997 | H5: 3.5% de CAPEX total inicial
A6: Energia camaras, OLT, NVR y core | B6: 2800 | C6: =B6 -> 2800 | D6: =C6*(1+'01 Supuestos'!$C$32) -> 2884 | E6: =D6*(1+'01 Supuestos'!$C$32) -> 2970.52 | F6: =E6*(1+'01 Supuestos'!$C$32) -> 3059.6356 | G6: =F6*(1+'01 Supuestos'!$C$32) -> 3151.4247 | H6: Consumo continuo de puntos y nodo central
A7: Canon/permisos de postacion | B7: 3200 | C7: =B7 -> 3200 | D7: =C7*(1+'01 Supuestos'!$C$32) -> 3296 | E7: =D7*(1+'01 Supuestos'!$C$32) -> 3394.88 | F7: =E7*(1+'01 Supuestos'!$C$32) -> 3496.7264 | G7: =F7*(1+'01 Supuestos'!$C$32) -> 3601.6282 | H7: Costo anual editable por uso de apoyos/postes
A8: Licencias VMS / monitoreo | B8: 3000 | C8: =B8 -> 3000 | D8: =C8*(1+'01 Supuestos'!$C$32) -> 3090 | E8: =D8*(1+'01 Supuestos'!$C$32) -> 3182.7 | F8: =E8*(1+'01 Supuestos'!$C$32) -> 3278.181 | G8: =F8*(1+'01 Supuestos'!$C$32) -> 3376.5264 | H8: Licencias, actualizaciones y soporte
A9: Backhaul / conectividad de respaldo | B9: 3600 | C9: =B9 -> 3600 | D9: =C9*(1+'01 Supuestos'!$C$32) -> 3708 | E9: =D9*(1+'01 Supuestos'!$C$32) -> 3819.24 | F9: =E9*(1+'01 Supuestos'!$C$32) -> 3933.8172 | G9: =F9*(1+'01 Supuestos'!$C$32) -> 4051.8317 | H9: Transporte o contingencia para centro de monitoreo
A10: Repuestos menores y vandalismo | B10: 2500 | C10: =B10 -> 2500 | D10: =C10*(1+'01 Supuestos'!$C$32) -> 2575 | E10: =D10*(1+'01 Supuestos'!$C$32) -> 2652.25 | F10: =E10*(1+'01 Supuestos'!$C$32) -> 2731.8175 | G10: =F10*(1+'01 Supuestos'!$C$32) -> 2813.772 | H10: Reposicion menor por dano o fallas
A11: Total OPEX | B11: =SUM(B4:B10) -> 30956.034 | C11: =SUM(C4:C10) -> 30956.034 | D11: =SUM(D4:D10) -> 31884.715 | E11: =SUM(E4:E10) -> 32841.256 | F11: =SUM(F4:F10) -> 33826.494 | G11: =SUM(G4:G10) -> 34841.289

Sheet 05 Depreciacion
A1: Depreciacion contable tecnica
A2: Base depreciable usada en el EERR; criterio lineal por vida util
A3: Tipo activo | B3: Base USD | C3: Vida util anos | D3: Depreciacion anual USD
A4: Activos tecnologicos | B4: =SUMIF('03 CAPEX'!$G$4:$G$21, 5, '03 CAPEX'!$F$4:$F$21) -> 36017.188 | C4: 5 | D4: =B4/C4 -> 7203.4375
A5: Pasivos / fibra / ODN | B5: =SUMIF('03 CAPEX'!$G$4:$G$21, 10, '03 CAPEX'!$F$4:$F$21) -> 65655.2 | C5: 10 | D5: =B5/C5 -> 6565.52
A6: Software/servicio capitalizable | B6: =SUMIF('03 CAPEX'!$G$4:$G$21, 3, '03 CAPEX'!$F$4:$F$21) -> 8500 | C6: 3 | D6: =B6/C6 -> 2833.3333
A7: Total depreciacion anual | B7: =SUM(B4:B6) -> 110172.39 | D7: =SUM(D4:D6) -> 16602.291

Sheet 06 EERR
A1: Estado de Resultados - EERR
A2: Criterio de lo devengado; proyecto estatal sin ingresos monetizados
A3: Concepto | B3: Año 1 | C3: Año 2 | D3: Año 3 | E3: Año 4 | F3: Año 5 | G3: Notas
A4: Ingresos comerciales directos | B4: ='01 Supuestos'!$C$33 -> 0 | C4: ='01 Supuestos'!$C$33 -> 0 | D4: ='01 Supuestos'!$C$33 -> 0 | E4: ='01 Supuestos'!$C$33 -> 0 | F4: ='01 Supuestos'!$C$33 -> 0 | G4: Base estatal: sin canon ni venta de servicio
A5: Beneficios monetizados / recuperos | B5: ='01 Supuestos'!$C$34 -> 0 | C5: ='01 Supuestos'!$C$34 -> 0 | D5: ='01 Supuestos'!$C$34 -> 0 | E5: ='01 Supuestos'!$C$34 -> 0 | F5: ='01 Supuestos'!$C$34 -> 0 | G5: No se monetizan beneficios sociales en el escenario base
A6: Ingresos / beneficios reconocidos | B6: =SUM(B4:B5) -> 0 | C6: =SUM(C4:C5) -> 0 | D6: =SUM(D4:D5) -> 0 | E6: =SUM(E4:E5) -> 0 | F6: =SUM(F4:F5) -> 0 | G6: Total reconocido en EERR
A7: OPEX | B7: =-'04 OPEX'!$C$11 -> -30956.034 | C7: =-'04 OPEX'!$D$11 -> -31884.715 | D7: =-'04 OPEX'!$E$11 -> -32841.256 | E7: =-'04 OPEX'!$F$11 -> -33826.494 | F7: =-'04 OPEX'!$G$11 -> -34841.289 | G7: Gastos operativos devengados
A8: EBITDA | B8: =SUM(B6:B7) -> -30956.034 | C8: =SUM(C6:C7) -> -31884.715 | D8: =SUM(D6:D7) -> -32841.256 | E8: =SUM(E6:E7) -> -33826.494 | F8: =SUM(F6:F7) -> -34841.289 | G8: Resultado antes de depreciacion
A9: Depreciacion | B9: =-'05 Depreciacion'!$D$7 -> -16602.291 | C9: =-'05 Depreciacion'!$D$7 -> -16602.291 | D9: =-'05 Depreciacion'!$D$7 -> -16602.291 | E9: =-'05 Depreciacion'!$D$7 -> -16602.291 | F9: =-'05 Depreciacion'!$D$7 -> -16602.291 | G9: Depreciacion lineal tecnica
A10: EBIT | B10: =SUM(B8:B9) -> -47558.324 | C10: =SUM(C8:C9) -> -48487.005 | D10: =SUM(D8:D9) -> -49443.547 | E10: =SUM(E8:E9) -> -50428.785 | F10: =SUM(F8:F9) -> -51443.579 | G10: Resultado operativo
A11: Impuesto a las ganancias | B11: =0 -> 0 | C11: =0 -> 0 | D11: =0 -> 0 | E11: =0 -> 0 | F11: =0 -> 0 | G11: No aplicable en escenario estatal
A12: Resultado neto | B12: =SUM(B10:B11) -> -47558.324 | C12: =SUM(C10:C11) -> -48487.005 | D12: =SUM(D10:D11) -> -49443.547 | E12: =SUM(E10:E11) -> -50428.785 | F12: =SUM(F10:F11) -> -51443.579 | G12: Resultado contable del periodo

Sheet 07 EFE Cash Flow
A1: Estado de Flujo de Efectivo - EFE / Cash Flow
A2: Actividades operativas, inversion y financiacion segun enfoque del PPT
A3: Concepto | B3: Año 0 | C3: Año 1 | D3: Año 2 | E3: Año 3 | F3: Año 4 | G3: Año 5 | H3: Notas
A4: Cobros por ingresos comerciales | B4: =0 -> 0 | C4: ='06 EERR'!$B$4 -> 0 | D4: ='06 EERR'!$C$4 -> 0 | E4: ='06 EERR'!$D$4 -> 0 | F4: ='06 EERR'!$E$4 -> 0 | G4: ='06 EERR'!$F$4 -> 0 | H4: Sin ingresos comerciales en escenario base
A5: Cobros por beneficios monetizados | B5: =0 -> 0 | C5: ='06 EERR'!$B$5 -> 0 | D5: ='06 EERR'!$C$5 -> 0 | E5: ='06 EERR'!$D$5 -> 0 | F5: ='06 EERR'!$E$5 -> 0 | G5: ='06 EERR'!$F$5 -> 0 | H5: No monetizado por defecto
A6: Pagos operativos OPEX | B6: =0 -> 0 | C6: =-'04 OPEX'!$C$11 -> -30956.034 | D6: =-'04 OPEX'!$D$11 -> -31884.715 | E6: =-'04 OPEX'!$E$11 -> -32841.256 | F6: =-'04 OPEX'!$F$11 -> -33826.494 | G6: =-'04 OPEX'!$G$11 -> -34841.289 | H6: Pagos de operacion y mantenimiento
A7: Flujo neto operativo | B7: =SUM(B4:B6) -> 0 | C7: =SUM(C4:C6) -> -30956.034 | D7: =SUM(D4:D6) -> -31884.715 | E7: =SUM(E4:E6) -> -32841.256 | F7: =SUM(F4:F6) -> -33826.494 | G7: =SUM(G4:G6) -> -34841.289 | H7: Operacion del proyecto
A8: CAPEX inicial | B8: =-'03 CAPEX'!$F$24 -> -121189.63 | C8: =0 -> 0 | D8: =0 -> 0 | E8: =0 -> 0 | F8: =0 -> 0 | G8: =0 -> 0 | H8: Inversion de implementacion
A9: CAPEX reposicion menor | B9: =0 -> 0 | C9: =-'03 CAPEX'!$F$24*'01 Supuestos'!$C$35 -> -2423.7925 | D9: =-'03 CAPEX'!$F$24*'01 Supuestos'!$C$35 -> -2423.7925 | E9: =-'03 CAPEX'!$F$24*'01 Supuestos'!$C$35 -> -2423.7925 | F9: =-'03 CAPEX'!$F$24*'01 Supuestos'!$C$35 -> -2423.7925 | G9: =-'03 CAPEX'!$F$24*'01 Supuestos'!$C$35 -> -2423.7925 | H9: Reposiciones menores anuales
A10: Valor residual / recupero | B10: =0 -> 0 | C10: =IF(C$2=5, '01 Supuestos'!$C$39, 0) -> 0 | D10: =IF(D$2=5, '01 Supuestos'!$C$39, 0) -> 0 | E10: =IF(E$2=5, '01 Supuestos'!$C$39, 0) -> 0 | F10: =IF(F$2=5, '01 Supuestos'!$C$39, 0) -> 0 | G10: =IF(G$2=5, '01 Supuestos'!$C$39, 0) -> 0 | H10: Conservador: cero por defecto
A11: Flujo neto de inversion | B11: =SUM(B8:B10) -> -121189.63 | C11: =SUM(C8:C10) -> -2423.7925 | D11: =SUM(D8:D10) -> -2423.7925 | E11: =SUM(E8:E10) -> -2423.7925 | F11: =SUM(F8:F10) -> -2423.7925 | G11: =SUM(G8:G10) -> -2423.7925 | H11: Inversion del proyecto
A12: Flujo libre del proyecto antes de financiacion | B12: =SUM(B7,B11) -> -121189.63 | C12: =SUM(C7,C11) -> -33379.826 | D12: =SUM(D7,D11) -> -34308.507 | E12: =SUM(E7,E11) -> -35265.049 | F12: =SUM(F7,F11) -> -36250.286 | G12: =SUM(G7,G11) -> -37265.081 | H12: Base para VAN; no incluye aporte presupuestario
A13: Aporte presupuestario estatal | B13: =-MIN(0,B12) -> 121189.63 | C13: =-MIN(0,C12) -> 33379.826 | D13: =-MIN(0,D12) -> 34308.507 | E13: =-MIN(0,E12) -> 35265.049 | F13: =-MIN(0,F12) -> 36250.286 | G13: =-MIN(0,G12) -> 37265.081 | H13: Financia deficit; no se usa para VAN del proyecto
A14: Deuda financiera | B14: =0 -> 0 | C14: =0 -> 0 | D14: =0 -> 0 | E14: =0 -> 0 | F14: =0 -> 0 | G14: =0 -> 0 | H14: No se asume deuda
A15: Flujo neto de financiacion | B15: =SUM(B13:B14) -> 121189.63 | C15: =SUM(C13:C14) -> 33379.826 | D15: =SUM(D13:D14) -> 34308.507 | E15: =SUM(E13:E14) -> 35265.049 | F15: =SUM(F13:F14) -> 36250.286 | G15: =SUM(G13:G14) -> 37265.081 | H15: Aportes/deuda
A16: Variacion neta de efectivo | B16: =SUM(B12,B15) -> 0 | C16: =SUM(C12,C15) -> 0 | D16: =SUM(D12,D15) -> 0 | E16: =SUM(E12,E15) -> 0 | F16: =SUM(F12,F15) -> 0 | G16: =SUM(G12,G15) -> 0 | H16: Cambio de caja luego de financiacion
A17: Caja inicial | B17: =0 -> 0 | C17: =B18 -> 0 | D17: =C18 -> 0 | E17: =D18 -> 0 | F17: =E18 -> 0 | G17: =F18 -> 0 | H17: Caja al inicio de cada año
A18: Caja final | B18: =SUM(B16,B17) -> 0 | C18: =SUM(C16,C17) -> 0 | D18: =SUM(D16,D17) -> 0 | E18: =SUM(E16,E17) -> 0 | F18: =SUM(F16,F17) -> 0 | G18: =SUM(G16,G17) -> 0 | H18: Caja final de cada ano

Sheet 08 VAN TIR
A1: Indicadores financieros
A2: VAN/TIR del flujo libre antes de financiacion; escenario estatal sin monetizar beneficios
A3: Indicador | B3: Valor | C3: Unidad | D3: Formula / criterio
A4: Tasa de descuento | B4: ='01 Supuestos'!$C$30 -> 0.15 | C4: % | D4: Input editable
A5: CAPEX total inicial | B5: ='03 CAPEX'!$F$24 -> 121189.63 | C5: USD | D5: Inversion ano 0
A6: OPEX Ano 1 | B6: ='04 OPEX'!$C$11 -> 30956.034 | C6: USD | D6: OPEX directo del Ano 1
A7: Resultado neto Ano 1 | B7: ='06 EERR'!$B$12 -> -47558.324 | C7: USD | D7: Resultado contable devengado
A8: Flujo libre Ano 0 | B8: ='07 EFE Cash Flow'!$B$12 -> -121189.63 | C8: USD | D8: Antes de financiacion
A9: VAN del flujo libre | B9: ='07 EFE Cash Flow'!$B$12+'07 EFE Cash Flow'!$C$12/(1+$B$4)^1+'07 EFE Cash Flow'!$D$12/(1+$B$4)^2+'07 EFE Cash Flow'!$E$12/(1+$B$4)^3+'07 EFE Cash Flow'!$F$12/(1+$B$4)^4+'07 EFE Cash Flow'!$G$12/(1+$B$4)^5 -> -238598.61 | C9: USD | D9: No incluye aporte presupuestario
A10: TIR del flujo libre | B10: No aplica | C10: % | D10: No aplica si todos los flujos son negativos
A11: Payback simple | B11: No recupera | C11: anos | D11: Sin ingresos monetizados, no recupera
A12: Necesidad presupuestaria total implementacion + 5 anos | B12: =SUM('07 EFE Cash Flow'!$B$13:$G$13) -> 297658.38 | C12: USD | D12: Aportes estatales acumulados para cubrir inversion inicial y operacion
A14: Concepto | B14: Año 0 | C14: Año 1 | D14: Año 2 | E14: Año 3 | F14: Año 4 | G14: ño 5
A15: Flujo libre antes de financiacion | B15: ='07 EFE Cash Flow'!$B$12 -> -121189.63 | C15: ='07 EFE Cash Flow'!$C$12 -> -33379.826 | D15: ='07 EFE Cash Flow'!$D$12 -> -34308.507 | E15: ='07 EFE Cash Flow'!$E$12 -> -35265.049 | F15: ='07 EFE Cash Flow'!$F$12 -> -36250.286 | G15: ='07 EFE Cash Flow'!$G$12 -> -37265.081
A16: Flujo acumulado | B16: =B15 -> -121189.63 | C16: =B16+C15 -> -154569.45 | D16: =C16+D15 -> -188877.96 | E16: =D16+E15 -> -224143.01 | F16: =E16+F15 -> -260393.29 | G16: =F16+G15 -> -297658.38
